LICENSE.txt
MANIFEST.in
README.rst
requirements.txt
setup.py
smartcat/__init__.py
smartcat/api.py
smartcat.egg-info/PKG-INFO
smartcat.egg-info/SOURCES.txt
smartcat.egg-info/dependency_links.txt
smartcat.egg-info/not-zip-safe
smartcat.egg-info/requires.txt
smartcat.egg-info/top_level.txt