Metadata-Version: 1.0
Name: smartcat
Version: 0.2.2
Summary: An SDK built to facilitate integration with SmartCAT API.
Home-page: https://github.com/gilyaev/smartcat-python-sdk
Author: Viktor Zhyliaiev
Author-email: gilyaev@gmail.com
License: Apache 2.0
Platform: UNKNOWN
